flowscribe/__init__.py
flowscribe/artifacts.py
flowscribe/catalog.py
flowscribe/config.py
flowscribe/core.py
flowscribe/main.py
flowscribe/privacy.py
flowscribe/sinks.py
flowscribe/sqlite_sink.py
flowscribe-0.1.1.dist-info/licenses/LICENSE
tests/test_flowscribe.py
tests/artifacts/test_artifact_writer.py
tests/cli/test_cli.py
tests/config/test_config_loader.py
tests/error_handling/test_missing_dependency.py
tests/privacy/test_redaction.py
tests/sinks/test_console_sink.py
tests/sinks/test_jsonl_sink.py
tests/sinks/test_sqlite_sink.py
flowscribe-0.1.1.dist-info/METADATA
flowscribe-0.1.1.dist-info/WHEEL
flowscribe-0.1.1.dist-info/top_level.txt
flowscribe-0.1.1.dist-info/RECORD
