Metadata-Version: 2.4
Name: flowscribe
Version: 0.1.1
Summary: Flow-first runtime tracing for Python apps.
Author-email: Your Name <your@email.com>
License: MIT License
Project-URL: Homepage, https://github.com/yourusername/flowscribe
Project-URL: Documentation, https://github.com/yourusername/flowscribe#readme
Project-URL: Repository, https://github.com/yourusername/flowscribe
Requires-Python: >=3.8
License-File: LICENSE
Requires-Dist: pyyaml>=6.0
Dynamic: license-file
